hoanggiakiet/__init__.py
hoanggiakiet/_aevents.py
hoanggiakiet/_client.py
hoanggiakiet/_core.py
hoanggiakiet/_exception.py
hoanggiakiet/_message.py
hoanggiakiet/_objects.py
hoanggiakiet/_package.py
hoanggiakiet/_parse_message.py
hoanggiakiet/_state.py
hoanggiakiet/_threads.py
hoanggiakiet/_util.py
hoanggiakiet/logging.py
hoanggiakiet/models.py
hoanggiakiet/Async/__init__.py
hoanggiakiet/Async/_async.py
hoanggiakiet/Async/_state.py
hoanggiakiet/simple/__init__.py
hoanggiakiet/simple/_async.py
hoanggiakiet/simple/_state.py
hoanggiakiet-2.0.7.dist-info/LICENSE
hoanggiakiet-2.0.7.dist-info/METADATA
hoanggiakiet-2.0.7.dist-info/WHEEL
hoanggiakiet-2.0.7.dist-info/top_level.txt
hoanggiakiet-2.0.7.dist-info/RECORD
