Metadata-Version: 2.1
Name: hoanggiakiet
Version: 2.0.7
Summary: hoanggiakiet: Customized Zalo API for Python
Author: Hoang Gia Kiet
Author-email: hoanggiakiet@gmail.com
Keywords: python,zalo,api,zalo api,zalo chat,requests,hoanggiakiet
Classifier: Development Status :: 3 - Alpha
Classifier: Intended Audience :: Developers
Classifier: License :: OSI Approved :: MIT License
Classifier: Operating System :: OS Independent
Classifier: Programming Language :: Python :: 3
License-File: LICENSE
Requires-Dist: requests
Requires-Dist: aiohttp
Requires-Dist: aenum
Requires-Dist: attr
Requires-Dist: pycryptodome
Requires-Dist: datetime
Requires-Dist: munch
Requires-Dist: websockets
